dynagatewaytypes/__init__.py
dynagatewaytypes/action_pb2.py
dynagatewaytypes/action_pb2_grpc.py
dynagatewaytypes/authentication_pb2.py
dynagatewaytypes/authentication_pb2_grpc.py
dynagatewaytypes/datatypes_pb2.py
dynagatewaytypes/datatypes_pb2_grpc.py
dynagatewaytypes/enums_pb2.py
dynagatewaytypes/enums_pb2_grpc.py
dynagatewaytypes/general_types_pb2.py
dynagatewaytypes/general_types_pb2_grpc.py
dynagatewaytypes/instance_pb2.py
dynagatewaytypes/instance_pb2_grpc.py
dynagatewaytypes/label_pb2.py
dynagatewaytypes/label_pb2_grpc.py
dynagatewaytypes/maintenance_pb2.py
dynagatewaytypes/maintenance_pb2_grpc.py
dynagatewaytypes/networkquery_pb2.py
dynagatewaytypes/networkquery_pb2_grpc.py
dynagatewaytypes/query_pb2.py
dynagatewaytypes/query_pb2_grpc.py
dynagatewaytypes/topology_pb2.py
dynagatewaytypes/topology_pb2_grpc.py
dynagatewaytypes-1.0.0.dist-info/METADATA
dynagatewaytypes-1.0.0.dist-info/WHEEL
dynagatewaytypes-1.0.0.dist-info/top_level.txt
dynagatewaytypes-1.0.0.dist-info/RECORD
