Metadata-Version: 2.1
Name: dynagatewaytypes
Version: 1.0.0
Summary: Python gRPC types for the Dynizer
Home-page: https://github.com/Dynactionize/dynagatewaytypes
Author: Dynactionize NV
Author-email: info-belgium@dynationize.com
License: UNKNOWN
Platform: UNKNOWN
Classifier: Programming Language :: Python :: 3
Classifier: License :: OSI Approved :: MIT License
Classifier: Operating System :: OS Independent
Requires-Dist: protobuf
Requires-Dist: grpcio
